{
	"name": "Mist Spider",
	"icon": "minecraft:spawn_egg{EntityTag:{id:'thejungle:lizardmanwitchdoctor'}}",
	"category": "helpers",
	"flag": "universalbestiary:entity:thejungle:lizardmanwitchdoctor",
	"advancement": "universalbestiary:thejungle_lizardmanwitchdoctor",
	"pages": [
		{
			"type": "text",
			"text": "The $(mob)Mist Spider$() is coming soon. Hang in there!"
		},
		{
			"type": "entity",
			"entity": "thejungle:lizardmanwitchdoctor",
			"text": "$(li)?? Health$()$(li)?? Damage$()"
		}
	]
}