{
	"name": "Wild Deer",
	"icon": "minecraft:spawn_egg{EntityTag:{id:'twilightforest:deer'}}",
	"category": "animals",
	"flag": "universalbestiary:entity:twilightforest:deer",
	"advancement": "universalbestiary:twilightforest_deer",
	"pages": [
		{
			"type": "text",
			"text": "The $(mob)Wild Deer$() is an animal found in the $(thing)Twilight Forest$(). It wanders around and flees when hit. It can be breed with $(item)Wheat$().$(p)Its meat is a good source of food."
		},
		{
			"type": "entity",
			"entity": "twilightforest:deer",
			"scale": 0.6,
			"offset": 0.4,
			"text": "$(li)10 Health$()"
		}
	]
}