{
	"name": "Death Tome",
	"icon": "minecraft:spawn_egg{EntityTag:{id:'twilightforest:death_tome'}}",
	"category": "monsters",
	"flag": "universalbestiary:entity:twilightforest:death_tome",
	"advancement": "universalbestiary:twilightforest_death_tome",
	"pages": [
		{
			"type": "text",
			"text": "The $(mob)Death Tome$() is a lorem ipsum dolor sit amet."
		},
		{
			"type": "entity",
			"entity": "twilightforest:death_tome",
			"offset": 0.5,
			"text": "$(li)?? Health$()$(li)?? Damage$()"
		},
		{
			"type": "spotlight",
			"item": "minecraft:rotten_flesh",
			"link_recipe": true,
			"text": "$(mob)Death Tomes$() drop $(item)Rottelesh$() on death."
		}
	]
}